sdg/__init__.py
sdg/metric/__init__.py
sdg/synthesizer/__init__.py
sdg/utils/__init__.py
SDG-0.0.1.dist-info/METADATA
SDG-0.0.1.dist-info/WHEEL
SDG-0.0.1.dist-info/top_level.txt
SDG-0.0.1.dist-info/RECORD
